{"swimmer":{"id":"10096 B","name_en":"Ko, Ka Chun","gender":"M","club_code":"PSC","club_history":[{"club_code":"HKG","first_seen":"2014-12-30","last_seen":"2014-12-30"},{"club_code":"PSC","first_seen":"2015-01-12","last_seen":"3/17/2015"}]},"personal_bests":{"lc":[{"swimmer_id":"10096 B","event_key":"backstroke_50_LC","distance":50,"stroke":"backstroke","course":"LC","time":"28.78","time_seconds":28.78,"competition_id":"428","date":"2015-09-01","age":19},{"swimmer_id":"10096 B","event_key":"breaststroke_50_LC","distance":50,"stroke":"breaststroke","course":"LC","time":"30.52","time_seconds":30.52,"competition_id":"428","date":"2015-09-01","age":19},{"swimmer_id":"10096 B","event_key":"butterfly_50_LC","distance":50,"stroke":"butterfly","course":"LC","time":"27.37","time_seconds":27.37,"competition_id":"412","date":"2015-01-12","age":18},{"swimmer_id":"10096 B","event_key":"freestyle_50_LC","distance":50,"stroke":"freestyle","course":"LC","time":"23.95","time_seconds":23.95,"competition_id":"444","date":"2016-04-18","age":20},{"swimmer_id":"10096 B","event_key":"breaststroke_100_LC","distance":100,"stroke":"breaststroke","course":"LC","time":"1:12.32","time_seconds":72.32,"competition_id":"431","date":"2015-11-11","age":19},{"swimmer_id":"10096 B","event_key":"freestyle_100_LC","distance":100,"stroke":"freestyle","course":"LC","time":"53.03","time_seconds":53.03,"competition_id":"428","date":"2015-09-01","age":19},{"swimmer_id":"10096 B","event_key":"freestyle_200_LC","distance":200,"stroke":"freestyle","course":"LC","time":"2:03.20","time_seconds":123.2,"competition_id":"431","date":"2015-11-11","age":19}],"sc":[{"swimmer_id":"10096 B","event_key":"breaststroke_50_SC","distance":50,"stroke":"breaststroke","course":"SC","time":"29.80","time_seconds":29.8,"competition_id":"423","date":"2015-06-08","age":19},{"swimmer_id":"10096 B","event_key":"butterfly_50_SC","distance":50,"stroke":"butterfly","course":"SC","time":"25.93","time_seconds":25.93,"competition_id":"442","date":"2016-03-14","age":20},{"swimmer_id":"10096 B","event_key":"freestyle_50_SC","distance":50,"stroke":"freestyle","course":"SC","time":"23.58","time_seconds":23.58,"competition_id":"442","date":"2016-03-14","age":20},{"swimmer_id":"10096 B","event_key":"breaststroke_100_SC","distance":100,"stroke":"breaststroke","course":"SC","time":"1:05.41","time_seconds":65.41,"competition_id":"426","date":"2015-07-24","age":19},{"swimmer_id":"10096 B","event_key":"freestyle_100_SC","distance":100,"stroke":"freestyle","course":"SC","time":"52.31","time_seconds":52.31,"competition_id":"442","date":"2016-03-14","age":20},{"swimmer_id":"10096 B","event_key":"individual_medley_100_SC","distance":100,"stroke":"individual_medley","course":"SC","time":"59.44","time_seconds":59.44,"competition_id":"442","date":"2016-03-14","age":20}]},"competition_count":13,"result_count":43,"last_competed":"3/17/2015","first_competed":"2015-01-12"}