{"swimmer":{"id":"24556 #IAZ","name_en":"Ng, Ka Ying","gender":"F","club_code":"PGS","club_history":[{"club_code":"PGS","first_seen":"2015-07-06","last_seen":"2016-03-07"}]},"personal_bests":{"lc":[{"swimmer_id":"24556 #IAZ","event_key":"backstroke_50_LC","distance":50,"stroke":"backstroke","course":"LC","time":"42.02","time_seconds":42.02,"competition_id":"425","date":"2015-07-06","age":15},{"swimmer_id":"24556 #IAZ","event_key":"freestyle_100_LC","distance":100,"stroke":"freestyle","course":"LC","time":"1:18.49","time_seconds":78.49,"competition_id":"425","date":"2015-07-06","age":15}],"sc":[{"swimmer_id":"24556 #IAZ","event_key":"breaststroke_50_SC","distance":50,"stroke":"breaststroke","course":"SC","time":"46.20","time_seconds":46.2,"competition_id":"441","date":"2016-03-07","age":16},{"swimmer_id":"24556 #IAZ","event_key":"freestyle_50_SC","distance":50,"stroke":"freestyle","course":"SC","time":"33.82","time_seconds":33.82,"competition_id":"438","date":"2016-01-28","age":16},{"swimmer_id":"24556 #IAZ","event_key":"freestyle_100_SC","distance":100,"stroke":"freestyle","course":"SC","time":"1:14.03","time_seconds":74.03,"competition_id":"432","date":"2016-01-12","age":15},{"swimmer_id":"24556 #IAZ","event_key":"individual_medley_100_SC","distance":100,"stroke":"individual_medley","course":"SC","time":"1:31.71","time_seconds":91.71,"competition_id":"438","date":"2016-01-28","age":16}]},"competition_count":4,"result_count":10,"last_competed":"2016-03-07","first_competed":"2015-07-06"}