{"swimmer":{"id":"26739 IAZ","name_en":"Poon, Cheuk Him","gender":"M","club_code":"SCA","club_history":[{"club_code":"SCA","first_seen":"2015-02-09","last_seen":"2016-01-12"}]},"personal_bests":{"lc":[{"swimmer_id":"26739 IAZ","event_key":"backstroke_50_LC","distance":50,"stroke":"backstroke","course":"LC","time":"47.59","time_seconds":47.59,"competition_id":"425","date":"2015-07-06","age":10},{"swimmer_id":"26739 IAZ","event_key":"breaststroke_50_LC","distance":50,"stroke":"breaststroke","course":"LC","time":"48.89","time_seconds":48.89,"competition_id":"425","date":"2015-07-06","age":10}],"sc":[{"swimmer_id":"26739 IAZ","event_key":"backstroke_50_SC","distance":50,"stroke":"backstroke","course":"SC","time":"43.50","time_seconds":43.5,"competition_id":"432","date":"2016-01-12","age":11},{"swimmer_id":"26739 IAZ","event_key":"breaststroke_100_SC","distance":100,"stroke":"breaststroke","course":"SC","time":"1:39.27","time_seconds":99.27,"competition_id":"432","date":"2016-01-12","age":11},{"swimmer_id":"26739 IAZ","event_key":"freestyle_100_SC","distance":100,"stroke":"freestyle","course":"SC","time":"1:27.74","time_seconds":87.74,"competition_id":"414","date":"2015-02-09","age":10}]},"competition_count":3,"result_count":12,"last_competed":"2016-01-12","first_competed":"2015-02-09"}