{"swimmer":{"id":"27577 B","name_en":"Law, Siu Kei","gender":"M","club_code":"DLS","club_history":[{"club_code":"DLS","first_seen":"2015-03-06","last_seen":"9/13/2016"}]},"personal_bests":{"lc":[{"swimmer_id":"27577 B","event_key":"backstroke_50_LC","distance":50,"stroke":"backstroke","course":"LC","time":"33.77","time_seconds":33.77,"competition_id":"475","date":"2017-06-26","age":13},{"swimmer_id":"27577 B","event_key":"butterfly_50_LC","distance":50,"stroke":"butterfly","course":"LC","time":"32.60","time_seconds":32.6,"competition_id":"473","date":"2017-06-05","age":13},{"swimmer_id":"27577 B","event_key":"freestyle_50_LC","distance":50,"stroke":"freestyle","course":"LC","time":"31.20","time_seconds":31.2,"competition_id":"421","date":"2015-05-11","age":11},{"swimmer_id":"27577 B","event_key":"backstroke_100_LC","distance":100,"stroke":"backstroke","course":"LC","time":"1:21.49","time_seconds":81.49,"competition_id":"421","date":"2015-05-11","age":11},{"swimmer_id":"27577 B","event_key":"breaststroke_100_LC","distance":100,"stroke":"breaststroke","course":"LC","time":"1:26.05","time_seconds":86.05,"competition_id":"473","date":"2017-06-05","age":13},{"swimmer_id":"27577 B","event_key":"butterfly_100_LC","distance":100,"stroke":"butterfly","course":"LC","time":"1:16.52","time_seconds":76.52,"competition_id":"439","date":"2016-02-22","age":12},{"swimmer_id":"27577 B","event_key":"freestyle_100_LC","distance":100,"stroke":"freestyle","course":"LC","time":"1:04.33","time_seconds":64.33,"competition_id":"475","date":"2017-06-26","age":13},{"swimmer_id":"27577 B","event_key":"backstroke_200_LC","distance":200,"stroke":"backstroke","course":"LC","time":"2:48.35","time_seconds":168.35,"competition_id":"472","date":"2017-05-29","age":13},{"swimmer_id":"27577 B","event_key":"freestyle_200_LC","distance":200,"stroke":"freestyle","course":"LC","time":"2:23.29","time_seconds":143.29,"competition_id":"473","date":"2017-06-05","age":13},{"swimmer_id":"27577 B","event_key":"individual_medley_200_LC","distance":200,"stroke":"individual_medley","course":"LC","time":"2:49.81","time_seconds":169.81,"competition_id":"429","date":"2015-09-07","age":11}],"sc":[{"swimmer_id":"27577 B","event_key":"butterfly_50_SC","distance":50,"stroke":"butterfly","course":"SC","time":"29.87","time_seconds":29.87,"competition_id":"482","date":"2017-12-04","age":14},{"swimmer_id":"27577 B","event_key":"freestyle_50_SC","distance":50,"stroke":"freestyle","course":"SC","time":"30.74","time_seconds":30.74,"competition_id":"440","date":"2016-03-03","age":12},{"swimmer_id":"27577 B","event_key":"backstroke_100_SC","distance":100,"stroke":"backstroke","course":"SC","time":"1:09.90","time_seconds":69.9,"competition_id":"482","date":"2017-12-04","age":14},{"swimmer_id":"27577 B","event_key":"breaststroke_100_SC","distance":100,"stroke":"breaststroke","course":"SC","time":"1:26.03","time_seconds":86.03,"competition_id":"432","date":"2016-01-12","age":12},{"swimmer_id":"27577 B","event_key":"individual_medley_100_SC","distance":100,"stroke":"individual_medley","course":"SC","time":"1:16.25","time_seconds":76.25,"competition_id":"440","date":"2016-03-03","age":12},{"swimmer_id":"27577 B","event_key":"freestyle_200_SC","distance":200,"stroke":"freestyle","course":"SC","time":"2:14.53","time_seconds":134.53,"competition_id":"482","date":"2017-12-04","age":14}]},"competition_count":12,"result_count":23,"last_competed":"2017-12-04","first_competed":"2015-03-06"}