{"swimmer":{"id":"30825 B","name_en":"Lee, Yuet Hin","gender":"M","club_code":"*LG","club_history":[{"club_code":"*LG","first_seen":"2018-01-16","last_seen":"2019-04-29"}]},"personal_bests":{"lc":[{"swimmer_id":"30825 B","event_key":"freestyle_200_LC","distance":200,"stroke":"freestyle","course":"LC","time":"2:34.38","time_seconds":154.38,"competition_id":"517","date":"2019-04-29","age":13}],"sc":[{"swimmer_id":"30825 B","event_key":"breaststroke_50_SC","distance":50,"stroke":"breaststroke","course":"SC","time":"44.76","time_seconds":44.76,"competition_id":"489","date":"2018-02-27","age":12},{"swimmer_id":"30825 B","event_key":"butterfly_50_SC","distance":50,"stroke":"butterfly","course":"SC","time":"36.49","time_seconds":36.49,"competition_id":"506","date":"2018-12-03","age":13},{"swimmer_id":"30825 B","event_key":"freestyle_50_SC","distance":50,"stroke":"freestyle","course":"SC","time":"30.93","time_seconds":30.93,"competition_id":"510","date":"","age":13},{"swimmer_id":"30825 B","event_key":"butterfly_100_SC","distance":100,"stroke":"butterfly","course":"SC","time":"1:31.49","time_seconds":91.49,"competition_id":"485","date":"2018-01-16","age":12},{"swimmer_id":"30825 B","event_key":"individual_medley_100_SC","distance":100,"stroke":"individual_medley","course":"SC","time":"1:19.83","time_seconds":79.83,"competition_id":"510","date":"","age":13}]},"competition_count":5,"result_count":8,"last_competed":"2019-04-29","first_competed":""}