{"swimmer":{"id":"31638 #IAZ","name_en":"Choi, Chi Him","gender":"M","club_code":"HTA","club_history":[{"club_code":"HTA","first_seen":"2017-06-05","last_seen":"2018-02-26"}]},"personal_bests":{"lc":[{"swimmer_id":"31638 #IAZ","event_key":"backstroke_50_LC","distance":50,"stroke":"backstroke","course":"LC","time":"35.32","time_seconds":35.32,"competition_id":"475","date":"2017-06-26","age":13},{"swimmer_id":"31638 #IAZ","event_key":"butterfly_50_LC","distance":50,"stroke":"butterfly","course":"LC","time":"32.60","time_seconds":32.6,"competition_id":"473","date":"2017-06-05","age":13},{"swimmer_id":"31638 #IAZ","event_key":"backstroke_200_LC","distance":200,"stroke":"backstroke","course":"LC","time":"2:57.57","time_seconds":177.57,"competition_id":"473","date":"2017-06-05","age":13},{"swimmer_id":"31638 #IAZ","event_key":"butterfly_200_LC","distance":200,"stroke":"butterfly","course":"LC","time":"2:51.08","time_seconds":171.08,"competition_id":"476","date":"2017-07-17","age":13},{"swimmer_id":"31638 #IAZ","event_key":"freestyle_200_LC","distance":200,"stroke":"freestyle","course":"LC","time":"2:25.32","time_seconds":145.32,"competition_id":"473","date":"2017-06-05","age":13},{"swimmer_id":"31638 #IAZ","event_key":"freestyle_400_LC","distance":400,"stroke":"freestyle","course":"LC","time":"4:49.01","time_seconds":289.01,"competition_id":"486","date":"2018-01-16","age":13}],"sc":[{"swimmer_id":"31638 #IAZ","event_key":"butterfly_50_SC","distance":50,"stroke":"butterfly","course":"SC","time":"30.64","time_seconds":30.64,"competition_id":"482","date":"2017-12-04","age":13},{"swimmer_id":"31638 #IAZ","event_key":"freestyle_50_SC","distance":50,"stroke":"freestyle","course":"SC","time":"28.80","time_seconds":28.8,"competition_id":"490","date":"2018-02-26","age":13},{"swimmer_id":"31638 #IAZ","event_key":"butterfly_100_SC","distance":100,"stroke":"butterfly","course":"SC","time":"1:07.58","time_seconds":67.58,"competition_id":"487","date":"2018-01-23","age":13},{"swimmer_id":"31638 #IAZ","event_key":"freestyle_100_SC","distance":100,"stroke":"freestyle","course":"SC","time":"1:02.17","time_seconds":62.17,"competition_id":"487","date":"2018-01-23","age":13},{"swimmer_id":"31638 #IAZ","event_key":"backstroke_200_SC","distance":200,"stroke":"backstroke","course":"SC","time":"2:44.12","time_seconds":164.12,"competition_id":"490","date":"2018-02-26","age":13},{"swimmer_id":"31638 #IAZ","event_key":"freestyle_200_SC","distance":200,"stroke":"freestyle","course":"SC","time":"2:12.02","time_seconds":132.02,"competition_id":"482","date":"2017-12-04","age":13}]},"competition_count":7,"result_count":12,"last_competed":"2018-02-26","first_competed":"2017-06-05"}