{"swimmer":{"id":"34651 #B","name_en":"Lee, Nok Sze","gender":"F","club_code":"*NW","club_history":[{"club_code":"*NW","first_seen":"2/20/2017","last_seen":"2017-07-17"}]},"personal_bests":{"lc":[{"swimmer_id":"34651 #B","event_key":"backstroke_100_LC","distance":100,"stroke":"backstroke","course":"LC","time":"1:32.09","time_seconds":92.09,"competition_id":"470","date":"2017-05-15","age":10},{"swimmer_id":"34651 #B","event_key":"butterfly_100_LC","distance":100,"stroke":"butterfly","course":"LC","time":"1:33.60","time_seconds":93.6,"competition_id":"476","date":"2017-07-17","age":10}],"sc":[{"swimmer_id":"34651 #B","event_key":"backstroke_100_SC","distance":100,"stroke":"backstroke","course":"SC","time":"1:31.34","time_seconds":91.34,"competition_id":"467","date":"2017-07-03","age":10},{"swimmer_id":"34651 #B","event_key":"breaststroke_100_SC","distance":100,"stroke":"breaststroke","course":"SC","time":"1:34.60","time_seconds":94.6,"competition_id":"474","date":"2017-06-12","age":10},{"swimmer_id":"34651 #B","event_key":"individual_medley_100_SC","distance":100,"stroke":"individual_medley","course":"SC","time":"1:31.04","time_seconds":91.04,"competition_id":"466","date":"2/20/2017","age":10}]},"competition_count":5,"result_count":6,"last_competed":"2017-07-17","first_competed":"2/20/2017"}