{"swimmer":{"id":"35907 B","name_en":"Lee, Lok Yi","gender":"F","club_code":"TPS","club_history":[{"club_code":"*CP","first_seen":"1/16/2017","last_seen":"2016-12-07"},{"club_code":"TPS","first_seen":"2018-11-12","last_seen":"2019-04-29"}]},"personal_bests":{"lc":[{"swimmer_id":"35907 B","event_key":"backstroke_50_LC","distance":50,"stroke":"backstroke","course":"LC","time":"49.88","time_seconds":49.88,"competition_id":"450","date":"2016-12-07","age":9},{"swimmer_id":"35907 B","event_key":"breaststroke_50_LC","distance":50,"stroke":"breaststroke","course":"LC","time":"54.10","time_seconds":54.1,"competition_id":"450","date":"2016-12-07","age":9},{"swimmer_id":"35907 B","event_key":"butterfly_50_LC","distance":50,"stroke":"butterfly","course":"LC","time":"43.14","time_seconds":43.14,"competition_id":"517","date":"2019-04-29","age":12},{"swimmer_id":"35907 B","event_key":"freestyle_200_LC","distance":200,"stroke":"freestyle","course":"LC","time":"2:58.97","time_seconds":178.97,"competition_id":"517","date":"2019-04-29","age":12}],"sc":[{"swimmer_id":"35907 B","event_key":"breaststroke_50_SC","distance":50,"stroke":"breaststroke","course":"SC","time":"59.16","time_seconds":59.16,"competition_id":"441","date":"2016-03-07","age":9},{"swimmer_id":"35907 B","event_key":"butterfly_50_SC","distance":50,"stroke":"butterfly","course":"SC","time":"42.69","time_seconds":42.69,"competition_id":"512","date":"","age":12},{"swimmer_id":"35907 B","event_key":"freestyle_50_SC","distance":50,"stroke":"freestyle","course":"SC","time":"38.33","time_seconds":38.33,"competition_id":"462","date":"1/16/2017","age":10},{"swimmer_id":"35907 B","event_key":"backstroke_100_SC","distance":100,"stroke":"backstroke","course":"SC","time":"1:33.01","time_seconds":93.01,"competition_id":"512","date":"","age":12},{"swimmer_id":"35907 B","event_key":"breaststroke_100_SC","distance":100,"stroke":"breaststroke","course":"SC","time":"1:40.42","time_seconds":100.42,"competition_id":"505","date":"2018-11-12","age":11},{"swimmer_id":"35907 B","event_key":"freestyle_100_SC","distance":100,"stroke":"freestyle","course":"SC","time":"1:15.23","time_seconds":75.23,"competition_id":"505","date":"2018-11-12","age":11}]},"competition_count":6,"result_count":10,"last_competed":"2019-04-29","first_competed":""}