{"swimmer":{"id":"36254 IAZ","name_en":"Wong, Yat Hei","gender":"M","club_code":"WTS","club_history":[{"club_code":"WTS","first_seen":"2018-11-12","last_seen":"2022-06-20"}]},"personal_bests":{"lc":[{"swimmer_id":"36254 IAZ","event_key":"backstroke_50_LC","distance":50,"stroke":"backstroke","course":"LC","time":"36.22","time_seconds":36.22,"competition_id":"4003","date":"2022-06-20","age":13},{"swimmer_id":"36254 IAZ","event_key":"backstroke_100_LC","distance":100,"stroke":"backstroke","course":"LC","time":"1:18.36","time_seconds":78.36,"competition_id":"3997","date":"2021-09-28","age":12},{"swimmer_id":"36254 IAZ","event_key":"individual_medley_200_LC","distance":200,"stroke":"individual_medley","course":"LC","time":"2:44.67","time_seconds":164.67,"competition_id":"4003","date":"2022-06-20","age":13}],"sc":[{"swimmer_id":"36254 IAZ","event_key":"backstroke_50_SC","distance":50,"stroke":"backstroke","course":"SC","time":"34.54","time_seconds":34.54,"competition_id":"4001","date":"2022-01-04","age":12},{"swimmer_id":"36254 IAZ","event_key":"breaststroke_50_SC","distance":50,"stroke":"breaststroke","course":"SC","time":"38.91","time_seconds":38.91,"competition_id":"4000","date":"2021-11-15","age":12},{"swimmer_id":"36254 IAZ","event_key":"butterfly_50_SC","distance":50,"stroke":"butterfly","course":"SC","time":"49.23","time_seconds":49.23,"competition_id":"512","date":"","age":9},{"swimmer_id":"36254 IAZ","event_key":"backstroke_100_SC","distance":100,"stroke":"backstroke","course":"SC","time":"1:36.09","time_seconds":96.09,"competition_id":"506","date":"2018-12-03","age":9},{"swimmer_id":"36254 IAZ","event_key":"butterfly_100_SC","distance":100,"stroke":"butterfly","course":"SC","time":"2:02.32","time_seconds":122.32,"competition_id":"510","date":"","age":9},{"swimmer_id":"36254 IAZ","event_key":"freestyle_100_SC","distance":100,"stroke":"freestyle","course":"SC","time":"1:30.19","time_seconds":90.19,"competition_id":"531","date":"2019-12-24","age":10}]},"competition_count":11,"result_count":16,"last_competed":"2022-06-20","first_competed":""}