{"swimmer":{"id":"38094 IAZ","name_en":"Wang, Chin Lam","gender":"F","club_code":"HTA","club_history":[{"club_code":"HTA","first_seen":"2017-04-18","last_seen":"3/16/2017"}]},"personal_bests":{"lc":[{"swimmer_id":"38094 IAZ","event_key":"breaststroke_50_LC","distance":50,"stroke":"breaststroke","course":"LC","time":"33.23","time_seconds":33.23,"competition_id":"469","date":"2017-04-18","age":16},{"swimmer_id":"38094 IAZ","event_key":"breaststroke_100_LC","distance":100,"stroke":"breaststroke","course":"LC","time":"1:12.61 qQT","time_seconds":72.61,"competition_id":"469","date":"2017-04-18","age":16},{"swimmer_id":"38094 IAZ","event_key":"breaststroke_200_LC","distance":200,"stroke":"breaststroke","course":"LC","time":"2:35.69 qQT","time_seconds":155.69,"competition_id":"469","date":"2017-04-18","age":16},{"swimmer_id":"38094 IAZ","event_key":"individual_medley_200_LC","distance":200,"stroke":"individual_medley","course":"LC","time":"2:30.14","time_seconds":150.14,"competition_id":"480","date":"2017-11-06","age":17}],"sc":[{"swimmer_id":"38094 IAZ","event_key":"breaststroke_50_SC","distance":50,"stroke":"breaststroke","course":"SC","time":"33.66","time_seconds":33.66,"competition_id":"468","date":"3/16/2017","age":16},{"swimmer_id":"38094 IAZ","event_key":"freestyle_50_SC","distance":50,"stroke":"freestyle","course":"SC","time":"27.80","time_seconds":27.8,"competition_id":"468","date":"3/16/2017","age":16},{"swimmer_id":"38094 IAZ","event_key":"breaststroke_100_SC","distance":100,"stroke":"breaststroke","course":"SC","time":"1:11.28","time_seconds":71.28,"competition_id":"468","date":"3/16/2017","age":16},{"swimmer_id":"38094 IAZ","event_key":"individual_medley_100_SC","distance":100,"stroke":"individual_medley","course":"SC","time":"1:08.43","time_seconds":68.43,"competition_id":"468","date":"3/16/2017","age":16},{"swimmer_id":"38094 IAZ","event_key":"breaststroke_200_SC","distance":200,"stroke":"breaststroke","course":"SC","time":"2:33.17","time_seconds":153.17,"competition_id":"468","date":"3/16/2017","age":16},{"swimmer_id":"38094 IAZ","event_key":"individual_medley_400_SC","distance":400,"stroke":"individual_medley","course":"SC","time":"5:11.90","time_seconds":311.9,"competition_id":"468","date":"3/16/2017","age":16}]},"competition_count":8,"result_count":29,"last_competed":"3/16/2017","first_competed":"2017-04-18"}