{"swimmer":{"id":"38574 B","name_en":"Ng, Kwan Ho","gender":"M","club_code":"TPS","club_history":[{"club_code":"TPS","first_seen":"2018-02-27","last_seen":"2022-09-05"}]},"personal_bests":{"lc":[{"swimmer_id":"38574 B","event_key":"backstroke_50_LC","distance":50,"stroke":"backstroke","course":"LC","time":"37.13","time_seconds":37.13,"competition_id":"3988","date":"2021-09-15","age":11},{"swimmer_id":"38574 B","event_key":"freestyle_50_LC","distance":50,"stroke":"freestyle","course":"LC","time":"28.55","time_seconds":28.55,"competition_id":"4006","date":"2022-09-05","age":13},{"swimmer_id":"38574 B","event_key":"freestyle_100_LC","distance":100,"stroke":"freestyle","course":"LC","time":"1:15.21","time_seconds":75.21,"competition_id":"3988","date":"2021-09-15","age":11}],"sc":[{"swimmer_id":"38574 B","event_key":"breaststroke_50_SC","distance":50,"stroke":"breaststroke","course":"SC","time":"1:01.26","time_seconds":61.26,"competition_id":"489","date":"2018-02-27","age":8},{"swimmer_id":"38574 B","event_key":"butterfly_50_SC","distance":50,"stroke":"butterfly","course":"SC","time":"49.71","time_seconds":49.71,"competition_id":"489","date":"2018-02-27","age":8}]},"competition_count":3,"result_count":5,"last_competed":"2022-09-05","first_competed":"2018-02-27"}