{"swimmer":{"id":"39576 #B","name_en":"Chan, Pak Yu","gender":"M","club_code":"CPS","club_history":[{"club_code":"SYS","first_seen":"2021-04-26","last_seen":"2022-01-04"},{"club_code":"CPS","first_seen":"2025-04-14","last_seen":"2026-03-16"}]},"personal_bests":{"lc":[{"swimmer_id":"39576 #B","event_key":"backstroke_50_LC","distance":50,"stroke":"backstroke","course":"LC","time":"45.12","time_seconds":45.12,"competition_id":"3996","date":"2021-09-23","age":10},{"swimmer_id":"39576 #B","event_key":"butterfly_50_LC","distance":50,"stroke":"butterfly","course":"LC","time":"40.63","time_seconds":40.63,"competition_id":"3984","date":"2021-04-26","age":10},{"swimmer_id":"39576 #B","event_key":"freestyle_50_LC","distance":50,"stroke":"freestyle","course":"LC","time":"35.44","time_seconds":35.44,"competition_id":"3997","date":"2021-09-28","age":10},{"swimmer_id":"39576 #B","event_key":"backstroke_100_LC","distance":100,"stroke":"backstroke","course":"LC","time":"1:36.03","time_seconds":96.03,"competition_id":"3997","date":"2021-09-28","age":10},{"swimmer_id":"39576 #B","event_key":"breaststroke_100_LC","distance":100,"stroke":"breaststroke","course":"LC","time":"2:00.34","time_seconds":120.34,"competition_id":"3984","date":"2021-04-26","age":10},{"swimmer_id":"39576 #B","event_key":"butterfly_100_LC","distance":100,"stroke":"butterfly","course":"LC","time":"1:04.87","time_seconds":64.87,"competition_id":"5152","date":"2025-09-07","age":14},{"swimmer_id":"39576 #B","event_key":"freestyle_100_LC","distance":100,"stroke":"freestyle","course":"LC","time":"1:18.30","time_seconds":78.3,"competition_id":"3988","date":"2021-09-15","age":10},{"swimmer_id":"39576 #B","event_key":"breaststroke_200_LC","distance":200,"stroke":"breaststroke","course":"LC","time":"2:57.32","time_seconds":177.32,"competition_id":"5132","date":"2025-08-27","age":14},{"swimmer_id":"39576 #B","event_key":"butterfly_200_LC","distance":200,"stroke":"butterfly","course":"LC","time":"2:20.11","time_seconds":140.11,"competition_id":"5161","date":"2025-11-03","age":15},{"swimmer_id":"39576 #B","event_key":"freestyle_200_LC","distance":200,"stroke":"freestyle","course":"LC","time":"2:04.45","time_seconds":124.45,"competition_id":"5161","date":"2025-11-03","age":15},{"swimmer_id":"39576 #B","event_key":"individual_medley_200_LC","distance":200,"stroke":"individual_medley","course":"LC","time":"2:26.45","time_seconds":146.45,"competition_id":"5152","date":"2025-09-07","age":14},{"swimmer_id":"39576 #B","event_key":"freestyle_400_LC","distance":400,"stroke":"freestyle","course":"LC","time":"4:24.91","time_seconds":264.91,"competition_id":"5161","date":"2025-11-03","age":15},{"swimmer_id":"39576 #B","event_key":"individual_medley_400_LC","distance":400,"stroke":"individual_medley","course":"LC","time":"5:06.86","time_seconds":306.86,"competition_id":"5135","date":"2025-08-18","age":14},{"swimmer_id":"39576 #B","event_key":"freestyle_800_LC","distance":800,"stroke":"freestyle","course":"LC","time":"9:07.15","time_seconds":547.15,"competition_id":"5161","date":"2025-11-03","age":15},{"swimmer_id":"39576 #B","event_key":"freestyle_1500_LC","distance":1500,"stroke":"freestyle","course":"LC","time":"17:16.80","time_seconds":1036.8,"competition_id":"5161","date":"2025-11-03","age":15}],"sc":[{"swimmer_id":"39576 #B","event_key":"backstroke_50_SC","distance":50,"stroke":"backstroke","course":"SC","time":"32.16","time_seconds":32.16,"competition_id":"5191","date":"2026-03-16","age":15},{"swimmer_id":"39576 #B","event_key":"breaststroke_50_SC","distance":50,"stroke":"breaststroke","course":"SC","time":"34.74","time_seconds":34.74,"competition_id":"5260","date":"2026-02-06","age":15},{"swimmer_id":"39576 #B","event_key":"butterfly_50_SC","distance":50,"stroke":"butterfly","course":"SC","time":"28.82","time_seconds":28.82,"competition_id":"5260","date":"2026-02-06","age":15},{"swimmer_id":"39576 #B","event_key":"backstroke_100_SC","distance":100,"stroke":"backstroke","course":"SC","time":"1:31.61","time_seconds":91.61,"competition_id":"4000","date":"2021-11-15","age":11},{"swimmer_id":"39576 #B","event_key":"butterfly_100_SC","distance":100,"stroke":"butterfly","course":"SC","time":"1:02.77","time_seconds":62.77,"competition_id":"5191","date":"2026-03-16","age":15},{"swimmer_id":"39576 #B","event_key":"butterfly_200_SC","distance":200,"stroke":"butterfly","course":"SC","time":"2:16.07","time_seconds":136.07,"competition_id":"5153","date":"2025-11-05","age":15},{"swimmer_id":"39576 #B","event_key":"freestyle_200_SC","distance":200,"stroke":"freestyle","course":"SC","time":"2:01.50","time_seconds":121.5,"competition_id":"5278","date":"2026-02-10","age":15},{"swimmer_id":"39576 #B","event_key":"freestyle_400_SC","distance":400,"stroke":"freestyle","course":"SC","time":"4:15.51","time_seconds":255.51,"competition_id":"5278","date":"2026-02-10","age":15},{"swimmer_id":"39576 #B","event_key":"individual_medley_400_SC","distance":400,"stroke":"individual_medley","course":"SC","time":"4:52.72","time_seconds":292.72,"competition_id":"5278","date":"2026-02-10","age":15},{"swimmer_id":"39576 #B","event_key":"freestyle_800_SC","distance":800,"stroke":"freestyle","course":"SC","time":"8:45.41","time_seconds":525.41,"competition_id":"5278","date":"2026-02-10","age":15},{"swimmer_id":"39576 #B","event_key":"freestyle_1500_SC","distance":1500,"stroke":"freestyle","course":"SC","time":"16:44.67","time_seconds":1004.67,"competition_id":"5153","date":"2025-11-05","age":15}]},"competition_count":17,"result_count":45,"last_competed":"2026-03-16","first_competed":"2021-04-26"}