{"swimmer":{"id":"41734 P","name_en":"Wu, Wai Ue","gender":"F","club_code":"DWA","club_history":[{"club_code":"DWA","first_seen":"2019-12-24","last_seen":"2019-12-24"}]},"personal_bests":{"lc":[],"sc":[{"swimmer_id":"41734 P","event_key":"freestyle_50_SC","distance":50,"stroke":"freestyle","course":"SC","time":"36.23","time_seconds":36.23,"competition_id":"510","date":"","age":11},{"swimmer_id":"41734 P","event_key":"freestyle_100_SC","distance":100,"stroke":"freestyle","course":"SC","time":"1:16.79","time_seconds":76.79,"competition_id":"531","date":"2019-12-24","age":12}]},"competition_count":2,"result_count":2,"last_competed":"2019-12-24","first_competed":""}