{"swimmer":{"id":"42458 IAZ","name_en":"Hon, Tsz Tung","gender":"F","club_code":"HTA","club_history":[{"club_code":"HTA","first_seen":"2018-11-12","last_seen":"2026-02-10"}]},"personal_bests":{"lc":[{"swimmer_id":"42458 IAZ","event_key":"backstroke_50_LC","distance":50,"stroke":"backstroke","course":"LC","time":"33.74","time_seconds":33.74,"competition_id":"5152","date":"2025-09-07","age":15},{"swimmer_id":"42458 IAZ","event_key":"breaststroke_50_LC","distance":50,"stroke":"breaststroke","course":"LC","time":"39.16","time_seconds":39.16,"competition_id":"4156","date":"2023-05-15","age":12},{"swimmer_id":"42458 IAZ","event_key":"butterfly_50_LC","distance":50,"stroke":"butterfly","course":"LC","time":"31.21","time_seconds":31.21,"competition_id":"5161","date":"2025-11-03","age":15},{"swimmer_id":"42458 IAZ","event_key":"freestyle_50_LC","distance":50,"stroke":"freestyle","course":"LC","time":"29.92","time_seconds":29.92,"competition_id":"4011","date":"2022-11-09","age":12},{"swimmer_id":"42458 IAZ","event_key":"backstroke_100_LC","distance":100,"stroke":"backstroke","course":"LC","time":"1:12.47","time_seconds":72.47,"competition_id":"5135","date":"2025-08-18","age":15},{"swimmer_id":"42458 IAZ","event_key":"breaststroke_100_LC","distance":100,"stroke":"breaststroke","course":"LC","time":"1:52.41","time_seconds":112.41,"competition_id":"519","date":"","age":8},{"swimmer_id":"42458 IAZ","event_key":"butterfly_100_LC","distance":100,"stroke":"butterfly","course":"LC","time":"1:08.47","time_seconds":68.47,"competition_id":"5161","date":"2025-11-03","age":15},{"swimmer_id":"42458 IAZ","event_key":"freestyle_100_LC","distance":100,"stroke":"freestyle","course":"LC","time":"1:09.19","time_seconds":69.19,"competition_id":"4003","date":"2022-06-20","age":12},{"swimmer_id":"42458 IAZ","event_key":"backstroke_200_LC","distance":200,"stroke":"backstroke","course":"LC","time":"2:37.82","time_seconds":157.82,"competition_id":"5046","date":"2025-04-14","age":14},{"swimmer_id":"42458 IAZ","event_key":"breaststroke_200_LC","distance":200,"stroke":"breaststroke","course":"LC","time":"3:10.50","time_seconds":190.5,"competition_id":"5132","date":"2025-08-27","age":15},{"swimmer_id":"42458 IAZ","event_key":"butterfly_200_LC","distance":200,"stroke":"butterfly","course":"LC","time":"2:43.12","time_seconds":163.12,"competition_id":"5052","date":"2025-07-24","age":15},{"swimmer_id":"42458 IAZ","event_key":"freestyle_200_LC","distance":200,"stroke":"freestyle","course":"LC","time":"2:13.76","time_seconds":133.76,"competition_id":"5161","date":"2025-11-03","age":15},{"swimmer_id":"42458 IAZ","event_key":"individual_medley_200_LC","distance":200,"stroke":"individual_medley","course":"LC","time":"2:32.70","time_seconds":152.7,"competition_id":"4721","date":"2024-11-18","age":14},{"swimmer_id":"42458 IAZ","event_key":"freestyle_400_LC","distance":400,"stroke":"freestyle","course":"LC","time":"4:47.07","time_seconds":287.07,"competition_id":"5135","date":"2025-08-18","age":15},{"swimmer_id":"42458 IAZ","event_key":"individual_medley_400_LC","distance":400,"stroke":"individual_medley","course":"LC","time":"5:31.44","time_seconds":331.44,"competition_id":"5052","date":"2025-07-24","age":15},{"swimmer_id":"42458 IAZ","event_key":"freestyle_800_LC","distance":800,"stroke":"freestyle","course":"LC","time":"9:56.49","time_seconds":596.49,"competition_id":"5052","date":"2025-07-24","age":15},{"swimmer_id":"42458 IAZ","event_key":"freestyle_1500_LC","distance":1500,"stroke":"freestyle","course":"LC","time":"20:04.46","time_seconds":1204.46,"competition_id":"4561","date":"2024-03-12","age":13}],"sc":[{"swimmer_id":"42458 IAZ","event_key":"backstroke_50_SC","distance":50,"stroke":"backstroke","course":"SC","time":"33.11","time_seconds":33.11,"competition_id":"4368","date":"2024-01-29","age":13},{"swimmer_id":"42458 IAZ","event_key":"breaststroke_50_SC","distance":50,"stroke":"breaststroke","course":"SC","time":"36.30","time_seconds":36.3,"competition_id":"4823","date":"2025-02-10","age":14},{"swimmer_id":"42458 IAZ","event_key":"butterfly_50_SC","distance":50,"stroke":"butterfly","course":"SC","time":"30.51","time_seconds":30.51,"competition_id":"4415","date":"2024-02-05","age":13},{"swimmer_id":"42458 IAZ","event_key":"freestyle_50_SC","distance":50,"stroke":"freestyle","course":"SC","time":"28.68","time_seconds":28.68,"competition_id":"4415","date":"2024-02-05","age":13},{"swimmer_id":"42458 IAZ","event_key":"backstroke_100_SC","distance":100,"stroke":"backstroke","course":"SC","time":"1:10.50","time_seconds":70.5,"competition_id":"4802","date":"2025-01-22","age":14},{"swimmer_id":"42458 IAZ","event_key":"breaststroke_100_SC","distance":100,"stroke":"breaststroke","course":"SC","time":"1:27.59","time_seconds":87.59,"competition_id":"4016","date":"2023-01-30","age":12},{"swimmer_id":"42458 IAZ","event_key":"butterfly_100_SC","distance":100,"stroke":"butterfly","course":"SC","time":"1:07.79","time_seconds":67.79,"competition_id":"5182","date":"2025-12-29","age":15},{"swimmer_id":"42458 IAZ","event_key":"freestyle_100_SC","distance":100,"stroke":"freestyle","course":"SC","time":"1:01.67","time_seconds":61.67,"competition_id":"4802","date":"2025-01-22","age":14},{"swimmer_id":"42458 IAZ","event_key":"individual_medley_100_SC","distance":100,"stroke":"individual_medley","course":"SC","time":"1:09.17","time_seconds":69.17,"competition_id":"4707","date":"2024-11-26","age":14},{"swimmer_id":"42458 IAZ","event_key":"backstroke_200_SC","distance":200,"stroke":"backstroke","course":"SC","time":"2:27.29","time_seconds":147.29,"competition_id":"4823","date":"2025-02-10","age":14},{"swimmer_id":"42458 IAZ","event_key":"butterfly_200_SC","distance":200,"stroke":"butterfly","course":"SC","time":"2:33.39","time_seconds":153.39,"competition_id":"5153","date":"2025-11-05","age":15},{"swimmer_id":"42458 IAZ","event_key":"freestyle_200_SC","distance":200,"stroke":"freestyle","course":"SC","time":"2:10.51","time_seconds":130.51,"competition_id":"5153","date":"2025-11-05","age":15},{"swimmer_id":"42458 IAZ","event_key":"individual_medley_200_SC","distance":200,"stroke":"individual_medley","course":"SC","time":"2:27.39","time_seconds":147.39,"competition_id":"4823","date":"2025-02-10","age":14},{"swimmer_id":"42458 IAZ","event_key":"freestyle_400_SC","distance":400,"stroke":"freestyle","course":"SC","time":"4:43.11","time_seconds":283.11,"competition_id":"5182","date":"2025-12-29","age":15},{"swimmer_id":"42458 IAZ","event_key":"individual_medley_400_SC","distance":400,"stroke":"individual_medley","course":"SC","time":"5:20.03","time_seconds":320.03,"competition_id":"4802","date":"2025-01-22","age":14},{"swimmer_id":"42458 IAZ","event_key":"freestyle_800_SC","distance":800,"stroke":"freestyle","course":"SC","time":"9:41.54","time_seconds":581.54,"competition_id":"5153","date":"2025-11-05","age":15},{"swimmer_id":"42458 IAZ","event_key":"freestyle_1500_SC","distance":1500,"stroke":"freestyle","course":"SC","time":"19:08.61","time_seconds":1148.61,"competition_id":"4802","date":"2025-01-22","age":14}]},"competition_count":46,"result_count":135,"last_competed":"2025-12-29","first_competed":""}