{"swimmer":{"id":"45474 #B","name_en":"Shek, Tsz Hang Jason","gender":"M","club_code":"HSW","club_history":[{"club_code":"TPS","first_seen":"2021-06-22","last_seen":"2022-01-07"},{"club_code":"HSW","first_seen":"2023-01-20","last_seen":"2023-12-12"}]},"personal_bests":{"lc":[{"swimmer_id":"45474 #B","event_key":"breaststroke_50_LC","distance":50,"stroke":"breaststroke","course":"LC","time":"37.27","time_seconds":37.27,"competition_id":"4188","date":"2023-06-19","age":12},{"swimmer_id":"45474 #B","event_key":"freestyle_50_LC","distance":50,"stroke":"freestyle","course":"LC","time":"28.96","time_seconds":28.96,"competition_id":"4296","date":"2023-06-10","age":12},{"swimmer_id":"45474 #B","event_key":"backstroke_100_LC","distance":100,"stroke":"backstroke","course":"LC","time":"1:28.06","time_seconds":88.06,"competition_id":"4193","date":"2023-07-05","age":12},{"swimmer_id":"45474 #B","event_key":"breaststroke_100_LC","distance":100,"stroke":"breaststroke","course":"LC","time":"1:24.50","time_seconds":84.5,"competition_id":"4066","date":"2023-04-27","age":12},{"swimmer_id":"45474 #B","event_key":"freestyle_100_LC","distance":100,"stroke":"freestyle","course":"LC","time":"1:08.04","time_seconds":68.04,"competition_id":"4265","date":"2023-09-11","age":12},{"swimmer_id":"45474 #B","event_key":"backstroke_200_LC","distance":200,"stroke":"backstroke","course":"LC","time":"3:13.46","time_seconds":193.46,"competition_id":"4041","date":"2023-04-11","age":12},{"swimmer_id":"45474 #B","event_key":"freestyle_200_LC","distance":200,"stroke":"freestyle","course":"LC","time":"2:31.53","time_seconds":151.53,"competition_id":"4041","date":"2023-04-11","age":12}],"sc":[{"swimmer_id":"45474 #B","event_key":"breaststroke_50_SC","distance":50,"stroke":"breaststroke","course":"SC","time":"43.22","time_seconds":43.22,"competition_id":"4000","date":"2021-11-15","age":10},{"swimmer_id":"45474 #B","event_key":"butterfly_50_SC","distance":50,"stroke":"butterfly","course":"SC","time":"43.32","time_seconds":43.32,"competition_id":"4000","date":"2021-11-15","age":10},{"swimmer_id":"45474 #B","event_key":"butterfly_100_SC","distance":100,"stroke":"butterfly","course":"SC","time":"1:32.80","time_seconds":92.8,"competition_id":"4015","date":"2023-01-20","age":11},{"swimmer_id":"45474 #B","event_key":"individual_medley_100_SC","distance":100,"stroke":"individual_medley","course":"SC","time":"1:18.73","time_seconds":78.73,"competition_id":"4023","date":"2023-05-12","age":12},{"swimmer_id":"45474 #B","event_key":"backstroke_200_SC","distance":200,"stroke":"backstroke","course":"SC","time":"3:08.26","time_seconds":188.26,"competition_id":"4019","date":"2023-03-06","age":12},{"swimmer_id":"45474 #B","event_key":"freestyle_200_SC","distance":200,"stroke":"freestyle","course":"SC","time":"2:31.00","time_seconds":151.0,"competition_id":"4319","date":"2023-12-12","age":12}]},"competition_count":17,"result_count":23,"last_competed":"2023-12-12","first_competed":"2021-06-22"}