{"swimmer":{"id":"46522","name_en":"@ICO Arrigoni, Olivia","gender":"F","club_code":"SCA","club_history":[{"club_code":"SCA","first_seen":"2021-09-27","last_seen":"2026-03-16"}]},"personal_bests":{"lc":[{"swimmer_id":"46522","event_key":"butterfly_50_LC","distance":50,"stroke":"butterfly","course":"LC","time":"34.39","time_seconds":34.39,"competition_id":"4563","date":"2024-04-29","age":15},{"swimmer_id":"46522","event_key":"freestyle_50_LC","distance":50,"stroke":"freestyle","course":"LC","time":"32.99","time_seconds":32.99,"competition_id":"4193","date":"2023-07-05","age":14},{"swimmer_id":"46522","event_key":"butterfly_100_LC","distance":100,"stroke":"butterfly","course":"LC","time":"1:19.74","time_seconds":79.74,"competition_id":"4193","date":"2023-07-05","age":14},{"swimmer_id":"46522","event_key":"freestyle_100_LC","distance":100,"stroke":"freestyle","course":"LC","time":"1:09.81","time_seconds":69.81,"competition_id":"4613","date":"2024-06-26","age":15},{"swimmer_id":"46522","event_key":"individual_medley_200_LC","distance":200,"stroke":"individual_medley","course":"LC","time":"2:57.23","time_seconds":177.23,"competition_id":"4613","date":"2024-06-26","age":15}],"sc":[{"swimmer_id":"46522","event_key":"backstroke_50_SC","distance":50,"stroke":"backstroke","course":"SC","time":"37.45","time_seconds":37.45,"competition_id":"5191","date":"2026-03-16","age":16},{"swimmer_id":"46522","event_key":"butterfly_50_SC","distance":50,"stroke":"butterfly","course":"SC","time":"33.04","time_seconds":33.04,"competition_id":"4802","date":"2025-01-22","age":15},{"swimmer_id":"46522","event_key":"freestyle_50_SC","distance":50,"stroke":"freestyle","course":"SC","time":"31.32","time_seconds":31.32,"competition_id":"4494","date":"2024-03-05","age":14},{"swimmer_id":"46522","event_key":"backstroke_100_SC","distance":100,"stroke":"backstroke","course":"SC","time":"1:20.74","time_seconds":80.74,"competition_id":"5260","date":"2026-02-06","age":16},{"swimmer_id":"46522","event_key":"butterfly_100_SC","distance":100,"stroke":"butterfly","course":"SC","time":"1:15.95","time_seconds":75.95,"competition_id":"4797","date":"2025-01-14","age":15},{"swimmer_id":"46522","event_key":"freestyle_100_SC","distance":100,"stroke":"freestyle","course":"SC","time":"1:08.93","time_seconds":68.93,"competition_id":"4797","date":"2025-01-14","age":15},{"swimmer_id":"46522","event_key":"individual_medley_100_SC","distance":100,"stroke":"individual_medley","course":"SC","time":"1:19.05","time_seconds":79.05,"competition_id":"4494","date":"2024-03-05","age":14}]},"competition_count":21,"result_count":33,"last_competed":"2026-03-16","first_competed":"2021-09-27"}