{"swimmer":{"id":"46776 IAZN","name_en":"Su, Yik Cheung","gender":"M","club_code":"WTS","club_history":[{"club_code":"WTS","first_seen":"2023-01-05","last_seen":"2026-03-16"}]},"personal_bests":{"lc":[],"sc":[{"swimmer_id":"46776 IAZN","event_key":"breaststroke_50_SC","distance":50,"stroke":"breaststroke","course":"SC","time":"53.48","time_seconds":53.48,"competition_id":"4014","date":"2023-01-05","age":10},{"swimmer_id":"46776 IAZN","event_key":"butterfly_50_SC","distance":50,"stroke":"butterfly","course":"SC","time":"49.19","time_seconds":49.19,"competition_id":"4014","date":"2023-01-05","age":10},{"swimmer_id":"46776 IAZN","event_key":"freestyle_50_SC","distance":50,"stroke":"freestyle","course":"SC","time":"27.49","time_seconds":27.49,"competition_id":"5332","date":"2026-03-16","age":14}]},"competition_count":2,"result_count":3,"last_competed":"2026-03-16","first_competed":"2023-01-05"}