{"swimmer":{"id":"47356 IAZ","name_en":"Kwok, Ho Wang","gender":"M","club_code":"SFC","club_history":[{"club_code":"SFC","first_seen":"2022-01-04","last_seen":"2023-01-20"}]},"personal_bests":{"lc":[{"swimmer_id":"47356 IAZ","event_key":"freestyle_50_LC","distance":50,"stroke":"freestyle","course":"LC","time":"29.13","time_seconds":29.13,"competition_id":"4006","date":"2022-09-05","age":13},{"swimmer_id":"47356 IAZ","event_key":"backstroke_100_LC","distance":100,"stroke":"backstroke","course":"LC","time":"1:21.60","time_seconds":81.6,"competition_id":"4010","date":"2022-11-15","age":13},{"swimmer_id":"47356 IAZ","event_key":"butterfly_100_LC","distance":100,"stroke":"butterfly","course":"LC","time":"1:16.25","time_seconds":76.25,"competition_id":"4010","date":"2022-11-15","age":13},{"swimmer_id":"47356 IAZ","event_key":"breaststroke_200_LC","distance":200,"stroke":"breaststroke","course":"LC","time":"3:19.37","time_seconds":199.37,"competition_id":"4006","date":"2022-09-05","age":13}],"sc":[{"swimmer_id":"47356 IAZ","event_key":"breaststroke_50_SC","distance":50,"stroke":"breaststroke","course":"SC","time":"37.19","time_seconds":37.19,"competition_id":"4012","date":"2022-12-30","age":13},{"swimmer_id":"47356 IAZ","event_key":"butterfly_50_SC","distance":50,"stroke":"butterfly","course":"SC","time":"33.13","time_seconds":33.13,"competition_id":"4012","date":"2022-12-30","age":13}]},"competition_count":3,"result_count":6,"last_competed":"2022-12-30","first_competed":"2022-09-05"}