{"swimmer":{"id":"49492 #B","name_en":"Au, Wing Cing","gender":"F","club_code":"TPS","club_history":[{"club_code":"TPS","first_seen":"2024-11-18","last_seen":"2025-07-30"}]},"personal_bests":{"lc":[{"swimmer_id":"49492 #B","event_key":"backstroke_50_LC","distance":50,"stroke":"backstroke","course":"LC","time":"36.47","time_seconds":36.47,"competition_id":"4721","date":"2024-11-18","age":10},{"swimmer_id":"49492 #B","event_key":"breaststroke_50_LC","distance":50,"stroke":"breaststroke","course":"LC","time":"40.54","time_seconds":40.54,"competition_id":"5102","date":"2025-07-30","age":11},{"swimmer_id":"49492 #B","event_key":"butterfly_50_LC","distance":50,"stroke":"butterfly","course":"LC","time":"35.36","time_seconds":35.36,"competition_id":"5102","date":"2025-07-30","age":11},{"swimmer_id":"49492 #B","event_key":"backstroke_100_LC","distance":100,"stroke":"backstroke","course":"LC","time":"1:15.27","time_seconds":75.27,"competition_id":"5052","date":"2025-07-24","age":11},{"swimmer_id":"49492 #B","event_key":"breaststroke_100_LC","distance":100,"stroke":"breaststroke","course":"LC","time":"1:30.48","time_seconds":90.48,"competition_id":"4721","date":"2024-11-18","age":10},{"swimmer_id":"49492 #B","event_key":"backstroke_200_LC","distance":200,"stroke":"backstroke","course":"LC","time":"2:44.56","time_seconds":164.56,"competition_id":"5102","date":"2025-07-30","age":11},{"swimmer_id":"49492 #B","event_key":"freestyle_200_LC","distance":200,"stroke":"freestyle","course":"LC","time":"2:32.52","time_seconds":152.52,"competition_id":"4721","date":"2024-11-18","age":10},{"swimmer_id":"49492 #B","event_key":"individual_medley_200_LC","distance":200,"stroke":"individual_medley","course":"LC","time":"2:52.54","time_seconds":172.54,"competition_id":"4721","date":"2024-11-18","age":10}],"sc":[{"swimmer_id":"49492 #B","event_key":"backstroke_50_SC","distance":50,"stroke":"backstroke","course":"SC","time":"34.98","time_seconds":34.98,"competition_id":"4823","date":"2025-02-10","age":10},{"swimmer_id":"49492 #B","event_key":"breaststroke_50_SC","distance":50,"stroke":"breaststroke","course":"SC","time":"38.68","time_seconds":38.68,"competition_id":"4730","date":"2024-12-30","age":10},{"swimmer_id":"49492 #B","event_key":"butterfly_50_SC","distance":50,"stroke":"butterfly","course":"SC","time":"33.42","time_seconds":33.42,"competition_id":"4802","date":"2025-01-22","age":10},{"swimmer_id":"49492 #B","event_key":"freestyle_50_SC","distance":50,"stroke":"freestyle","course":"SC","time":"32.04","time_seconds":32.04,"competition_id":"4730","date":"2024-12-30","age":10},{"swimmer_id":"49492 #B","event_key":"backstroke_100_SC","distance":100,"stroke":"backstroke","course":"SC","time":"1:14.68","time_seconds":74.68,"competition_id":"4802","date":"2025-01-22","age":10},{"swimmer_id":"49492 #B","event_key":"breaststroke_100_SC","distance":100,"stroke":"breaststroke","course":"SC","time":"1:26.63","time_seconds":86.63,"competition_id":"4823","date":"2025-02-10","age":10},{"swimmer_id":"49492 #B","event_key":"butterfly_100_SC","distance":100,"stroke":"butterfly","course":"SC","time":"1:18.73","time_seconds":78.73,"competition_id":"4797","date":"2025-01-14","age":10},{"swimmer_id":"49492 #B","event_key":"freestyle_100_SC","distance":100,"stroke":"freestyle","course":"SC","time":"1:09.31","time_seconds":69.31,"competition_id":"4802","date":"2025-01-22","age":10},{"swimmer_id":"49492 #B","event_key":"individual_medley_100_SC","distance":100,"stroke":"individual_medley","course":"SC","time":"1:17.12","time_seconds":77.12,"competition_id":"4707","date":"2024-11-26","age":10},{"swimmer_id":"49492 #B","event_key":"backstroke_200_SC","distance":200,"stroke":"backstroke","course":"SC","time":"2:41.82","time_seconds":161.82,"competition_id":"4911","date":"2025-03-19","age":11},{"swimmer_id":"49492 #B","event_key":"freestyle_200_SC","distance":200,"stroke":"freestyle","course":"SC","time":"2:27.01","time_seconds":147.01,"competition_id":"4707","date":"2024-11-26","age":10},{"swimmer_id":"49492 #B","event_key":"individual_medley_200_SC","distance":200,"stroke":"individual_medley","course":"SC","time":"2:40.35","time_seconds":160.35,"competition_id":"4823","date":"2025-02-10","age":10}]},"competition_count":9,"result_count":26,"last_competed":"2025-07-30","first_competed":"2024-11-18"}