{"swimmer":{"id":"50320","name_en":"@ICX Yin, Jiayong","gender":"M","club_code":"CPS","club_history":[{"club_code":"CPS","first_seen":"2023-06-19","last_seen":"2023-12-12"}]},"personal_bests":{"lc":[{"swimmer_id":"50320","event_key":"breaststroke_50_LC","distance":50,"stroke":"breaststroke","course":"LC","time":"39.20","time_seconds":39.2,"competition_id":"4188","date":"2023-06-19","age":11},{"swimmer_id":"50320","event_key":"butterfly_50_LC","distance":50,"stroke":"butterfly","course":"LC","time":"29.82","time_seconds":29.82,"competition_id":"4188","date":"2023-06-19","age":11},{"swimmer_id":"50320","event_key":"freestyle_100_LC","distance":100,"stroke":"freestyle","course":"LC","time":"1:03.91","time_seconds":63.91,"competition_id":"4188","date":"2023-06-19","age":11}],"sc":[{"swimmer_id":"50320","event_key":"butterfly_50_SC","distance":50,"stroke":"butterfly","course":"SC","time":"28.72","time_seconds":28.72,"competition_id":"4346","date":"2023-12-12","age":12}]},"competition_count":2,"result_count":4,"last_competed":"2023-12-12","first_competed":"2023-06-19"}