{"swimmer":{"id":"51359 IAZ","name_en":"Chan, Nigel Angelo","gender":"M","club_code":"SCA","club_history":[{"club_code":"SCA","first_seen":"2023-12-05","last_seen":"2026-03-16"}]},"personal_bests":{"lc":[{"swimmer_id":"51359 IAZ","event_key":"backstroke_50_LC","distance":50,"stroke":"backstroke","course":"LC","time":"40.28","time_seconds":40.28,"competition_id":"5152","date":"2025-09-07","age":10},{"swimmer_id":"51359 IAZ","event_key":"breaststroke_50_LC","distance":50,"stroke":"breaststroke","course":"LC","time":"1:06.41","time_seconds":66.41,"competition_id":"4250","date":"2023-12-05","age":8},{"swimmer_id":"51359 IAZ","event_key":"backstroke_100_LC","distance":100,"stroke":"backstroke","course":"LC","time":"1:30.18","time_seconds":90.18,"competition_id":"5132","date":"2025-08-27","age":10},{"swimmer_id":"51359 IAZ","event_key":"breaststroke_100_LC","distance":100,"stroke":"breaststroke","course":"LC","time":"1:57.00","time_seconds":117.0,"competition_id":"5015","date":"2025-05-12","age":10},{"swimmer_id":"51359 IAZ","event_key":"freestyle_100_LC","distance":100,"stroke":"freestyle","course":"LC","time":"1:21.24","time_seconds":81.24,"competition_id":"5037","date":"2025-06-09","age":10}],"sc":[{"swimmer_id":"51359 IAZ","event_key":"backstroke_50_SC","distance":50,"stroke":"backstroke","course":"SC","time":"38.07","time_seconds":38.07,"competition_id":"5191","date":"2026-03-16","age":11},{"swimmer_id":"51359 IAZ","event_key":"backstroke_100_SC","distance":100,"stroke":"backstroke","course":"SC","time":"1:33.37","time_seconds":93.37,"competition_id":"5031","date":"2024-12-09","age":10},{"swimmer_id":"51359 IAZ","event_key":"individual_medley_100_SC","distance":100,"stroke":"individual_medley","course":"SC","time":"1:31.73","time_seconds":91.73,"competition_id":"4932","date":"2025-03-26","age":10}]},"competition_count":9,"result_count":10,"last_competed":"2026-03-16","first_competed":"2023-12-05"}