{"swimmer":{"id":"51573 B","name_en":"Lam, Hoi Ching Camille","gender":"F","club_code":"WTS","club_history":[{"club_code":"WTS","first_seen":"2023-12-16","last_seen":"2026-02-06"}]},"personal_bests":{"lc":[],"sc":[{"swimmer_id":"51573 B","event_key":"breaststroke_50_SC","distance":50,"stroke":"breaststroke","course":"SC","time":"1:07.88","time_seconds":67.88,"competition_id":"4366","date":"2023-12-16","age":8},{"swimmer_id":"51573 B","event_key":"freestyle_100_SC","distance":100,"stroke":"freestyle","course":"SC","time":"1:38.53","time_seconds":98.53,"competition_id":"4932","date":"2025-03-26","age":9},{"swimmer_id":"51573 B","event_key":"individual_medley_100_SC","distance":100,"stroke":"individual_medley","course":"SC","time":"1:47.58","time_seconds":107.58,"competition_id":"4932","date":"2025-03-26","age":9}]},"competition_count":2,"result_count":3,"last_competed":"2025-03-26","first_competed":"2023-12-16"}