{"swimmer":{"id":"52484 IAZ","name_en":"Hung, Hin Yeung Sherlock","gender":"M","club_code":"*WA","club_history":[{"club_code":"*WA","first_seen":"2024-02-06","last_seen":"2024-03-01"}]},"personal_bests":{"lc":[],"sc":[{"swimmer_id":"52484 IAZ","event_key":"backstroke_50_SC","distance":50,"stroke":"backstroke","course":"SC","time":"48.94","time_seconds":48.94,"competition_id":"4397","date":"2024-02-06","age":8},{"swimmer_id":"52484 IAZ","event_key":"freestyle_50_SC","distance":50,"stroke":"freestyle","course":"SC","time":"41.55","time_seconds":41.55,"competition_id":"4421","date":"2024-03-01","age":8},{"swimmer_id":"52484 IAZ","event_key":"breaststroke_100_SC","distance":100,"stroke":"breaststroke","course":"SC","time":"2:03.60","time_seconds":123.6,"competition_id":"4421","date":"2024-03-01","age":8},{"swimmer_id":"52484 IAZ","event_key":"freestyle_100_SC","distance":100,"stroke":"freestyle","course":"SC","time":"1:40.60","time_seconds":100.6,"competition_id":"4397","date":"2024-02-06","age":8}]},"competition_count":2,"result_count":4,"last_competed":"2024-03-01","first_competed":"2024-02-06"}