{"swimmer":{"id":"52538 #IAZ","name_en":"Mok, Chi Lam","gender":"F","club_code":"LWS","club_history":[{"club_code":"LWS","first_seen":"2025-08-27","last_seen":"2025-08-27"}]},"personal_bests":{"lc":[{"swimmer_id":"52538 #IAZ","event_key":"freestyle_50_LC","distance":50,"stroke":"freestyle","course":"LC","time":"34.35","time_seconds":34.35,"competition_id":"5132","date":"2025-08-27","age":12},{"swimmer_id":"52538 #IAZ","event_key":"butterfly_100_LC","distance":100,"stroke":"butterfly","course":"LC","time":"1:32.87","time_seconds":92.87,"competition_id":"5132","date":"2025-08-27","age":12}],"sc":[]},"competition_count":1,"result_count":2,"last_competed":"2025-08-27","first_competed":"2025-08-27"}