{"swimmer":{"id":"54995 IAZ","name_en":"Tam, Ka Chung","gender":"M","club_code":"PSC","club_history":[{"club_code":"PSC","first_seen":"2024-12-23","last_seen":"2025-03-26"}]},"personal_bests":{"lc":[],"sc":[{"swimmer_id":"54995 IAZ","event_key":"breaststroke_50_SC","distance":50,"stroke":"breaststroke","course":"SC","time":"55.36","time_seconds":55.36,"competition_id":"4889","date":"2024-12-23","age":10},{"swimmer_id":"54995 IAZ","event_key":"butterfly_50_SC","distance":50,"stroke":"butterfly","course":"SC","time":"48.21","time_seconds":48.21,"competition_id":"4889","date":"2024-12-23","age":10},{"swimmer_id":"54995 IAZ","event_key":"freestyle_100_SC","distance":100,"stroke":"freestyle","course":"SC","time":"1:32.40","time_seconds":92.4,"competition_id":"4932","date":"2025-03-26","age":10},{"swimmer_id":"54995 IAZ","event_key":"individual_medley_100_SC","distance":100,"stroke":"individual_medley","course":"SC","time":"1:49.33","time_seconds":109.33,"competition_id":"4932","date":"2025-03-26","age":10}]},"competition_count":2,"result_count":4,"last_competed":"2025-03-26","first_competed":"2024-12-23"}